okrouter/__init__.py
okrouter-0.1.0.dist-info/LICENSE
okrouter-0.1.0.dist-info/METADATA
okrouter-0.1.0.dist-info/WHEEL
okrouter-0.1.0.dist-info/top_level.txt
okrouter-0.1.0.dist-info/RECORD
