Metadata-Version: 2.1
Name: okrouter
Version: 0.1.0
Summary: The official Python client for OKRouter API
Home-page: https://okrouter.com
Author: OKRouter Team
Author-email: support@okrouter.com
Project-URL: Documentation, https://okrouter.com/docs
Project-URL: Source Code, https://github.com/okrouter/okrouter-python
Project-URL: Website, https://okrouter.com
Classifier: Programming Language :: Python :: 3
Classifier: License :: OSI Approved :: MIT License
Classifier: Operating System :: OS Independent
Classifier: Topic :: Software Development :: Libraries :: Python Modules
Classifier: Topic :: Internet :: WWW/HTTP
Requires-Python: >=3.6
License-File: LICENSE
Requires-Dist: requests
